LICENSE
MANIFEST.in
README.rst
VERSION
requirements.txt
setup.cfg
setup.py
test-requirements.txt
pywebhooks/__init__.py
pywebhooks/app.py
pywebhooks.egg-info/PKG-INFO
pywebhooks.egg-info/SOURCES.txt
pywebhooks.egg-info/dependency_links.txt
pywebhooks.egg-info/entry_points.txt
pywebhooks.egg-info/not-zip-safe
pywebhooks.egg-info/requires.txt
pywebhooks.egg-info/top_level.txt
pywebhooks/api/__init__.py
pywebhooks/api/decorators/__init__.py
pywebhooks/api/decorators/authorization.py
pywebhooks/api/decorators/validation.py
pywebhooks/api/handlers/__init__.py
pywebhooks/api/handlers/pagination_handler.py
pywebhooks/api/handlers/resources_handler.py
pywebhooks/api/resources/__init__.py
pywebhooks/api/resources/v1/__init__.py
pywebhooks/api/resources/v1/account/__init__.py
pywebhooks/api/resources/v1/account/account_api.py
pywebhooks/api/resources/v1/account/accounts_api.py
pywebhooks/api/resources/v1/account/reset/__init__.py
pywebhooks/api/resources/v1/account/reset/api_key_api.py
pywebhooks/api/resources/v1/account/reset/secret_key_api.py
pywebhooks/api/resources/v1/webhook/__init__.py
pywebhooks/api/resources/v1/webhook/registration_api.py
pywebhooks/api/resources/v1/webhook/registrations_api.py
pywebhooks/api/resources/v1/webhook/subscription.py
pywebhooks/api/resources/v1/webhook/subscriptions.py
pywebhooks/api/resources/v1/webhook/triggered_api.py
pywebhooks/database/__init__.py
pywebhooks/database/rethinkdb/__init__.py
pywebhooks/database/rethinkdb/bootstrap_admin.py
pywebhooks/database/rethinkdb/drop.py
pywebhooks/database/rethinkdb/initialize.py
pywebhooks/database/rethinkdb/interactions.py
pywebhooks/examples/__init__.py
pywebhooks/examples/endpoint_development_server.py
pywebhooks/tasks/__init__.py
pywebhooks/tasks/webhook_notification.py
pywebhooks/utils/__init__.py
pywebhooks/utils/common.py
pywebhooks/utils/request_handler.py
pywebhooks/utils/rethinkdb_helper.py
tests/__init__.py
tests/functional/__init__.py
tests/functional/http_interactions.py
tests/unit/__init__.py
tests/unit/test_app.py
tests/unit/api/__init__.py
tests/unit/api/decorators/__init__.py
tests/unit/api/decorators/test_authorization.py
tests/unit/api/decorators/test_validation.py
tests/unit/api/handlers/__init__.py
