Metadata-Version: 1.1
Name: pywebhooks
Version: 0.5.5
Summary: WebHooks Service
Home-page: https://github.com/chadlung/pywebhooks
Author: Chad Lung
Author-email: chad.lung@gmail.com
License: UNKNOWN
Keywords: WebHooks
Platform: UNKNOWN
Classifier: Programming Language :: Python :: 3.6
Classifier: Development Status :: 4 - Beta
Classifier: Environment :: Web Environment
Classifier: Intended Audience :: Developers
Classifier: License :: OSI Approved :: Apache Software License
Classifier: Operating System :: MacOS :: MacOS X
Classifier: Operating System :: POSIX :: Linux
